vscaledriver/__init__.py
vscaledriver-0.9.0.dist-info/LICENSE
vscaledriver-0.9.0.dist-info/METADATA
vscaledriver-0.9.0.dist-info/WHEEL
vscaledriver-0.9.0.dist-info/top_level.txt
vscaledriver-0.9.0.dist-info/RECORD
