Metadata-Version: 2.1
Name: vscaledriver
Version: 0.9.0
Summary: Libcloud driver for vds.selectel.ru (vscale.io)
Home-page: https://github.com/thebits/libcloud-vscale
Author: Sergey Mezentsev
Author-email: thebits@yandex.ru
License: UNLICENSE
Classifier: Intended Audience :: System Administrators
Classifier: Operating System :: OS Independent
Classifier: Programming Language :: Python :: 3
License-File: LICENSE
Requires-Dist: apache-libcloud (>=3.0.0)
